aws_secrets_cache/__init__.py
aws_secrets_cache-0.2.1.dist-info/LICENSE
aws_secrets_cache-0.2.1.dist-info/METADATA
aws_secrets_cache-0.2.1.dist-info/WHEEL
aws_secrets_cache-0.2.1.dist-info/RECORD
