Metadata-Version: 2.1
Name: aws-secrets-cache
Version: 0.2.1
Summary: 
License: BSD-3-Clause
Author: Łukasz Kostka
Author-email: lukasz.kostka@mirumee.com
Requires-Python: >=3.9,<4.0
Classifier: License :: OSI Approved :: BSD License
Classifier: Programming Language :: Python :: 3
Classifier: Programming Language :: Python :: 3.9
Classifier: Programming Language :: Python :: 3.10
Classifier: Programming Language :: Python :: 3.11
Requires-Dist: boto3 (>=1.26.163,<2.0.0)
